{"api-examples.md":"Cul20NdD","docs__app.md":"D7bTcmTD","docs_app-containers.md":"CiG0mi9D","docs_cache.md":"9n0cubyO","docs_configuration.md":"C-v-7f4I","docs_console.md":"Cgpct4E1","docs_contribution.md":"_S8wAxFf","docs_controllers.md":"CEXHvfgf","docs_databases_getting-started.md":"CGuz1i2U","docs_databases_migrations.md":"c9-q1eX8","docs_databases_models.md":"BbUfCg5o","docs_databases_repository.md":"BVYF63rM","docs_directory-structure.md":"BRlBgJje","docs_error-handling.md":"CSKa8yma","docs_events.md":"Btyq-lFo","docs_execution-context.md":"Bz-A262O","docs_file-storage.md":"DGnJfKk6","docs_first-project.md":"DWIRpNOm","docs_guards.md":"BGQilLTX","docs_helpers.md":"Da9nAwXE","docs_installation.md":"DQ0krLrO","docs_localization.md":"CUfB6nX1","docs_logging.md":"BS2GDPwg","docs_mailers.md":"Bq0UItY9","docs_middlewares.md":"AYX3RMRA","docs_providers.md":"DHHcnOIc","docs_queues.md":"gq8UR4Uc","docs_reflectors.md":"CSVbI-_-","docs_requests.md":"BiuLBV8-","docs_response.md":"BlmasYNZ","docs_service-providers.md":"1AhBj7fj","docs_services.md":"Dx1A9fRB","docs_transformers.md":"C1EaTSTy","docs_validation.md":"Cs-h_0BX","index.md":"C5VUU7zw","markdown-examples.md":"CZn_pcOJ"}
